pertdata/__init__.py
pertdata/pert_dataset.py
pertdata/utils.py
pertdata/version.py
pertdata/resources/DixitRegev2016.json
pertdata/resources/NormanWeissman2019_filtered.json
pertdata/resources/ReplogleWeissman2022_K562_essential.json
pertdata/resources/ReplogleWeissman2022_rpe1.json
pertdata/resources/adamson.json
pertdata/resources/dixit.json
pertdata/resources/norman.json
pertdata/resources/replogle_k562_essential.json
pertdata/resources/replogle_rpe1_essential.json
pertdata/resources/wessel_dataset.json
pertdata-1.1.5.dist-info/METADATA
pertdata-1.1.5.dist-info/WHEEL
pertdata-1.1.5.dist-info/licenses/LICENSE
pertdata-1.1.5.dist-info/RECORD
