Metadata-Version: 2.4
Name: pertdata
Version: 1.1.5
Summary: Functionality for Handling Perturbation Datasets
Project-URL: Repository, https://github.com/voges/pertdata.git
Author-email: Jan Voges <jvoges@external.unav.es>, Guillermo Dufort y Álvarez <gdufortyalv@unav.es>
License: MIT License
License-File: LICENSE
Requires-Python: >=3.10
Requires-Dist: anndata>=0.11.3
Requires-Dist: appdirs>=1.4.4
Requires-Dist: ipykernel>=6.29.5
Requires-Dist: pandas>=2.2.3
Requires-Dist: requests>=2.32.3
Requires-Dist: scanpy>=1.10.4
Requires-Dist: scikit-learn>=1.6.1
Requires-Dist: tqdm>=4.67.1
